icpp/__init__.py
icpp/__main__.py
icpp/call_function_from_name.py
icpp/commands_build_library.py
icpp/commands_build_library_native.py
icpp/commands_build_native.py
icpp/commands_build_wasm.py
icpp/commands_get.py
icpp/commands_init.py
icpp/commands_install_rust.py
icpp/commands_install_wasi_sdk.py
icpp/config_default.py
icpp/conftest_base.py
icpp/decorators.py
icpp/icpp_toml.py
icpp/options_build.py
icpp/options_main.py
icpp/py.typed
icpp/run_dfx_cmd.py
icpp/run_shell_cmd.py
icpp/smoketest.py
icpp/utils.py
icpp/version.py
icpp/version_ic_wasi_polyfill.py
icpp/version_rust.py
icpp/version_wasi2ic.py
icpp/version_wasi_sdk.py
icpp/canisters/greet/README.md
icpp/canisters/greet/demo-c++17.sh
icpp/canisters/greet/demo.sh
icpp/canisters/greet/dfx.json
icpp/canisters/greet/icpp-c++17.toml
icpp/canisters/greet/icpp.toml
icpp/canisters/greet/libhello/hello.cpp
icpp/canisters/greet/libhello/hello.h
icpp/canisters/greet/libworld/world.cpp
icpp/canisters/greet/libworld/world.h
icpp/canisters/greet/native/main.cpp
icpp/canisters/greet/native/main.h
icpp/canisters/greet/src/greet.cpp
icpp/canisters/greet/src/greet.did
icpp/canisters/greet/src/greet.h
icpp/canisters/greet/src/vendors/nlohmann/json/json.hpp
icpp/canisters/greet/test/__init__.py
icpp/canisters/greet/test/conftest.py
icpp/canisters/greet/test/test_apis.py
icpp/ic/canister/canister.h
icpp/ic/canister/canister_base.cpp
icpp/ic/canister/canister_base.h
icpp/ic/canister/canister_cleanup_callback.cpp
icpp/ic/canister/canister_cleanup_callback.h
icpp/ic/canister/canister_global_timer.cpp
icpp/ic/canister/canister_global_timer.h
icpp/ic/canister/canister_heartbeat.cpp
icpp/ic/canister/canister_heartbeat.h
icpp/ic/canister/canister_init.cpp
icpp/ic/canister/canister_init.h
icpp/ic/canister/canister_inspect_message.cpp
icpp/ic/canister/canister_inspect_message.h
icpp/ic/canister/canister_post_upgrade.cpp
icpp/ic/canister/canister_post_upgrade.h
icpp/ic/canister/canister_pre_upgrade.cpp
icpp_pro-5.3.0.dist-info/licenses/LICENSE
icpp_pro-5.3.0.dist-info/METADATA
icpp_pro-5.3.0.dist-info/WHEEL
icpp_pro-5.3.0.dist-info/entry_points.txt
icpp_pro-5.3.0.dist-info/top_level.txt
icpp_pro-5.3.0.dist-info/RECORD
