Metadata-Version: 2.4
Name: icpp-pro
Version: 5.3.0
Summary: C++ Canister Development Kit (CDK) for the Internet Computer
Author-email: icpp-pro <icpp@icpp.world>
Maintainer-email: icpp-pro <icpp@icpp.world>
License: MIT License
Project-URL: Homepage, https://www.onicai.com/
Project-URL: Documentation, https://docs.icpp.world/
Project-URL: Repository, https://github.com/icppWorld/icpp-pro
Project-URL: Issues, https://github.com/icppWorld/icpp-pro/issues
Project-URL: Changelog, https://docs.icpp.world/release-notes.html#changelog
Keywords: Internet Computer,C++,Canister Development Kit,CDK,Smart Contracts,blockchain
Classifier: Development Status :: 4 - Beta
Classifier: License :: OSI Approved :: MIT License
Classifier: Programming Language :: Python :: 3
Classifier: Programming Language :: Python :: 3.9
Classifier: Programming Language :: Python :: 3.10
Classifier: Programming Language :: Python :: 3.11
Classifier: Programming Language :: Python :: 3.12
Classifier: Programming Language :: Python :: 3 :: Only
Classifier: Operating System :: POSIX :: Linux
Classifier: Operating System :: MacOS
Requires-Python: >=3.9
License-File: LICENSE
Requires-Dist: icpp-candid>=5.3.0
Requires-Dist: icpp-pro-is-not-supported-on-windows; platform_system == "Windows"
Requires-Dist: typer[all]>=0.9.0
Requires-Dist: tomli
Requires-Dist: requests
Requires-Dist: enlighten
Requires-Dist: pytest
Provides-Extra: dev
Requires-Dist: black==23.12.1; extra == "dev"
Requires-Dist: pylint==2.13.9; extra == "dev"
Requires-Dist: mypy==1.8.0; extra == "dev"
Requires-Dist: build==1.2.2; extra == "dev"
Requires-Dist: twine==6.0.1; extra == "dev"
Requires-Dist: mkdocs==1.5.3; extra == "dev"
Requires-Dist: types-requests==2.31.0.10; extra == "dev"
Dynamic: license-file
